pw_hash/__init__.py
pw_hash_mod-0.0.1.dist-info/LICENSE
pw_hash_mod-0.0.1.dist-info/METADATA
pw_hash_mod-0.0.1.dist-info/WHEEL
pw_hash_mod-0.0.1.dist-info/top_level.txt
pw_hash_mod-0.0.1.dist-info/RECORD
