Metadata-Version: 2.1
Name: pw-hash-mod
Version: 0.0.1
Summary: Provide PWHash class to generate hash string with random salt.
Home-page: https://github.com/andy19910102/PWHash.py
Author: Huang An Sheng
Author-email: andy19910102@gmail.com
License: UNKNOWN
Platform: UNKNOWN
Classifier: Programming Language :: Python :: 3
Classifier: License :: OSI Approved :: MIT License
Classifier: Operating System :: OS Independent
Requires-Python: >=3.6
